p1_auth/__init__.py
p1_auth/admin.py
p1_auth/apps.py
p1_auth/backends.py
p1_auth/callables.py
p1_auth/middleware.py
p1_auth/models.py
p1_auth/tests.py
p1_auth/views.py
p1_auth/migrations/0001_initial.py
p1_auth/migrations/__init__.py
p1_auth-0.2.4.dist-info/METADATA
p1_auth-0.2.4.dist-info/WHEEL
p1_auth-0.2.4.dist-info/top_level.txt
p1_auth-0.2.4.dist-info/RECORD
