Metadata-Version: 2.4
Name: p1-auth
Version: 0.2.4
Summary: Installable Django Authentication that adds support for Platform One
Home-page: https://github.com/OpenLXP/p1-auth/
Author: OpenLXP
Author-email: openlxphost@gmail.com
License: MIT
Classifier: Development Status :: 4 - Beta
Classifier: Environment :: Web Environment
Classifier: Framework :: Django :: 4.2
Classifier: Intended Audience :: Developers
Classifier: Operating System :: OS Independent
Classifier: Programming Language :: Python :: 3 :: Only
Classifier: Programming Language :: Python :: 3.7
Classifier: Programming Language :: Python :: Implementation :: CPython
Classifier: Topic :: Software Development :: Libraries :: Application Frameworks
Classifier: Topic :: Software Development :: Libraries :: Python Modules
Requires-Python: >=3.7
Requires-Dist: PyJWT>=2.0.0
Requires-Dist: djangorestframework>=3.13.0
